{
	"configurations" : 
	[
		{
			"directories" : 
			[
				{
					"build" : ".",
					"childIndexes" : 
					[
						1,
						2
					],
					"jsonFile" : "directory-.-Release-d0094a50bb2071803777.json",
					"minimumCMakeVersion" : 
					{
						"string" : "3.8"
					},
					"projectIndex" : 0,
					"source" : "."
				},
				{
					"build" : "MyCMakeLibrary",
					"jsonFile" : "directory-MyCMakeLibrary-Release-43db1392914cf4387e80.json",
					"minimumCMakeVersion" : 
					{
						"string" : "3.8"
					},
					"parentIndex" : 0,
					"projectIndex" : 0,
					"source" : "MyCMakeLibrary",
					"targetIndexes" : 
					[
						0
					]
				},
				{
					"build" : "MyCPlusPlusCmakeProject",
					"jsonFile" : "directory-MyCPlusPlusCmakeProject-Release-c2d1f1b70af475387a58.json",
					"minimumCMakeVersion" : 
					{
						"string" : "3.8"
					},
					"parentIndex" : 0,
					"projectIndex" : 0,
					"source" : "MyCPlusPlusCmakeProject",
					"targetIndexes" : 
					[
						1
					]
				}
			],
			"name" : "Release",
			"projects" : 
			[
				{
					"directoryIndexes" : 
					[
						0,
						1,
						2
					],
					"name" : "MyCPlusPlusCmakeProject",
					"targetIndexes" : 
					[
						0,
						1
					]
				}
			],
			"targets" : 
			[
				{
					"directoryIndex" : 1,
					"id" : "CMakeLibrary::@7fdb502f8e2dfca8537c",
					"jsonFile" : "target-CMakeLibrary-Release-bdde47318d077156874d.json",
					"name" : "CMakeLibrary",
					"projectIndex" : 0
				},
				{
					"directoryIndex" : 2,
					"id" : "MyCMakeProject::@f511cb6b8c3134743e82",
					"jsonFile" : "target-MyCMakeProject-Release-b21e2f030b2d822e6427.json",
					"name" : "MyCMakeProject",
					"projectIndex" : 0
				}
			]
		}
	],
	"kind" : "codemodel",
	"paths" : 
	{
		"build" : "D:/Projects/Visual Studio Projects/MyCPlusPlusCmakeProject/out/build/x64-release",
		"source" : "D:/Projects/Visual Studio Projects/MyCPlusPlusCmakeProject"
	},
	"version" : 
	{
		"major" : 2,
		"minor" : 6
	}
}
